<Properties GitUserInfo="UsingGIT" StartupConfiguration="{85746ECD-50F5-49AD-A6EE-A34CD632C853}|ProjectApp">
  <MonoDevelop.Ide.Workbench>
    <Files>
      <File FileName="ProjectApp/Views/Home/_PieChartData.cshtml" Line="34" Column="54" />
      <File FileName="ProjectApp/Controllers/ProjectController.cs" Line="150" Column="59" />
      <File FileName="ProjectApp/Models/ProjectViewModel.cs" Line="20" Column="25" />
      <File FileName="ProjectApp/Views/Project/Index.cshtml" Line="40" Column="25" />
      <File FileName="ProjectApp/Views/Project/Detail.cshtml" Line="13" Column="33" />
      <File FileName="ProjectApp/Views/Project/AddorEdit.cshtml" Line="50" Column="8" />
      <File FileName="ProjectApp/Controllers/HomeController.cs" Line="79" Column="122" />
    </Files>
    <Pads>
      <Pad Id="ProjectPad">
        <State name="__root__">
          <Node name="ProjectApp" expanded="True">
            <Node name="Solution Items" expanded="True" />
            <Node name="ProjectApp" expanded="True">
              <Node name="Areas" expanded="True">
                <Node name="Identity" expanded="True">
                  <Node name="Data" expanded="True" />
                  <Node name="Pages" expanded="True" />
                </Node>
              </Node>
              <Node name="Controllers" expanded="True" />
              <Node name="Migrations" expanded="True">
                <Node name="ProjectDB" expanded="True" />
              </Node>
              <Node name="Models" expanded="True" />
              <Node name="Properties" expanded="True" />
              <Node name="Views" expanded="True">
                <Node name="Home" expanded="True" />
                <Node name="Project" expanded="True">
                  <Node name="Index.cshtml" selected="True" />
                </Node>
                <Node name="Shared" expanded="True" />
              </Node>
              <Node name="wwwroot" expanded="True">
                <Node name="css" expanded="True" />
                <Node name="js" expanded="True" />
              </Node>
              <Node name="appsettings.json" expanded="True" />
            </Node>
          </Node>
        </State>
      </Pad>
    </Pads>
  </MonoDevelop.Ide.Workbench>
  <MonoDevelop.Ide.DebuggingService.PinnedWatches />
  <MonoDevelop.Ide.Workspace ActiveConfiguration="Debug" />
  <MonoDevelop.Ide.DebuggingService.Breakpoints>
    <BreakpointStore />
  </MonoDevelop.Ide.DebuggingService.Breakpoints>
  <MultiItemStartupConfigurations />
  <MonoDevelop.Ide.ItemProperties.ProjectApp PreferredExecutionTarget="/Applications/Google Chrome.app" />
</Properties>